minirag/__init__.py
minirag/base.py
minirag/exceptions.py
minirag/llm.py
minirag/minirag.py
minirag/operate.py
minirag/prompt.py
minirag/utils.py
minirag_hku-0.0.2.dist-info/LICENSE
minirag_hku-0.0.2.dist-info/METADATA
minirag_hku-0.0.2.dist-info/WHEEL
minirag_hku-0.0.2.dist-info/top_level.txt
minirag_hku-0.0.2.dist-info/RECORD
