Metadata-Version: 2.2
Name: minirag-hku
Version: 0.0.2
Summary: MiniRAG: Towards Extremely Simple Retrieval-Augmented Generation
Home-page: https://github.com/HKUDS/MiniRAG
Author: Tianyu Fan
Classifier: Development Status :: 4 - Beta
Classifier: Programming Language :: Python :: 3
Classifier: License :: OSI Approved :: MIT License
Classifier: Operating System :: OS Independent
Classifier: Intended Audience :: Developers
Classifier: Topic :: Software Development :: Libraries :: Python Modules
Requires-Python: >=3.9
License-File: LICENSE
Dynamic: home-page
Dynamic: requires-python
